README.md
kvae.py
setup.py
kvae.egg-info/PKG-INFO
kvae.egg-info/SOURCES.txt
kvae.egg-info/dependency_links.txt
kvae.egg-info/top_level.txt
kvae.egg-info/zip-safe