Metadata-Version: 1.1
Name: kvae
Version: 0.0.1
Summary: keras varational_autoencoder as a package
Home-page: http://github.com/pwaller/kvae/
Author: Peter Waller
Author-email: p@pwaller.net
License: MIT
Keywords: vae variational autoencoder keras tensorflow
Platform: UNKNOWN
Classifier: License :: OSI Approved :: MIT License
Classifier: Programming Language :: Python :: 3.7
